badger/__init__.py
badger/cli.py
badger_cli-0.1.0.dist-info/LICENSE
badger_cli-0.1.0.dist-info/METADATA
badger_cli-0.1.0.dist-info/WHEEL
badger_cli-0.1.0.dist-info/entry_points.txt
badger_cli-0.1.0.dist-info/top_level.txt
badger_cli-0.1.0.dist-info/RECORD
