Metadata-Version: 2.1
Name: badger-cli
Version: 0.1.0
Summary: A CLI for Badger Commerce
Home-page: https://github.com/Badger-Commerce/badger-cli
Author: Your Name
Author-email: chris.kellet@bdgr.co.uk
Classifier: Programming Language :: Python :: 3
Classifier: License :: OSI Approved :: MIT License
Classifier: Operating System :: OS Independent
Requires-Python: >=3.6
License-File: LICENSE
